qfs/__init__.py
qfs/cli.py
qfs/converter.py
qfs/file_system.py
qfs/quantum_cipher.py
quantum_file_system-0.1.1.dist-info/licenses/LICENSE
quantum_file_system-0.1.1.dist-info/METADATA
quantum_file_system-0.1.1.dist-info/WHEEL
quantum_file_system-0.1.1.dist-info/entry_points.txt
quantum_file_system-0.1.1.dist-info/top_level.txt
quantum_file_system-0.1.1.dist-info/RECORD
