Metadata-Version: 2.4
Name: quantum-file-system
Version: 0.1.1
Summary: A secure web-based file conversion system that encrypts JSON files into QJSON format using custom quantum-inspired encryption algorithms.
Home-page: https://github.com/Cipher-Prime/quantum-file-system.git
Author: QFS Development Team
Author-email: QFS Development Team <cipher_nexus@icloud.com>
License: 
Project-URL: Repository, https://github.com/Cipher-Prime/quantum-file-system.git
Keywords: encryption,quantum,file-system,security,json
Classifier: Development Status :: 4 - Beta
Classifier: Intended Audience :: Developers
Classifier: Topic :: Security :: Cryptography
Classifier: Topic :: System :: Filesystems
Classifier: Programming Language :: Python :: 3
Classifier: Programming Language :: Python :: 3.11
Classifier: License :: OSI Approved :: MIT License
Classifier: Operating System :: OS Independent
Requires-Python: >=3.11
License-File: LICENSE
Requires-Dist: flask>=3.1.1
Requires-Dist: werkzeug>=3.1.3
Requires-Dist: gunicorn>=23.0.0
Dynamic: author
Dynamic: home-page
Dynamic: license-file
Dynamic: requires-python
